mask_to_polygons/__init__.py
mask_to_polygons/vectorification.py
mask_to_polygons/processing/__init__.py
mask_to_polygons/processing/buildings.py
mask_to_polygons/processing/denoise.py
mask_to_polygons/processing/polygons.py
mask_to_polygons/processing/score.py
mask_to_polygons/simplification/__init__.py
mask_to_polygons/simplification/rectilinear.py
mask_to_polygons-0.0.2.dist-info/LICENSE
mask_to_polygons-0.0.2.dist-info/METADATA
mask_to_polygons-0.0.2.dist-info/WHEEL
mask_to_polygons-0.0.2.dist-info/top_level.txt
mask_to_polygons-0.0.2.dist-info/RECORD
