Metadata-Version: 2.1
Name: mask-to-polygons
Version: 0.0.2
Summary: Routines for extracting and working with polygons from semantic segmentation masks
Home-page: https://github.com/azavea/mask-to-polygons
Author: James McClain
Author-email: jmcclain@azava.com
License: Apache License 2.0
Platform: UNKNOWN
Requires-Dist: Shapely (==1.6.*)
Requires-Dist: opencv-python (==4.1.*)
Requires-Dist: numpy (>=1.0.0)
Requires-Dist: rasterio (>=1.0.0)
Requires-Dist: geojson (>=2.4.0)
